playbook/__init__.py
playbook/__version__.py
playbook/cli.py
playbook/command.py
playbook/config.py
playbook/main.py
playbook/utils.py
youqu_playbook-2025.1.7.dist-info/METADATA
youqu_playbook-2025.1.7.dist-info/WHEEL
youqu_playbook-2025.1.7.dist-info/entry_points.txt
youqu_playbook-2025.1.7.dist-info/licenses/LICENSE
youqu_playbook-2025.1.7.dist-info/RECORD
