Metadata-Version: 2.1
Name: youqu-playbook
Version: 2025.1.7
Summary: Task Scheduling System
Author-email: mikigo <huangmingqiang@uniontech.com>
License: GPL2.0
License-File: LICENSE
Requires-Python: >=3.6
Requires-Dist: click
Requires-Dist: funnylog2
Requires-Dist: nocmd
